{
  "titulo": "Acuerdo DEL EJECUTIVO DEL ESTADO POR EL QUE SE DA A CONOCER EL IMPORTE DE LAS PARTICIPACIONES FEDERA",
  "Contenido": "LAS PARTICIPACIONES FEDERALES ENTREGADAS A LOS MUNICIPIOS, EN EL PERÍODO\nARTICULO 6° DE LA LEY DE COORDINACION FISCAL.\nLIC. CARLOS MIGUEL AYSA GONZÁLEZ, Gobernador del Estado de Campeche, en ejercicio de las facultades que me confieren las fracciones IX, XIX y XXXVII del artículo 71 y el artículo 73 de la\nCampeche; los artículos 1, 3, 4, 5, 6, 7, 8, 9, 10 y 25 de la Ley del Sistema de Coordinación Fiscal del Estado de Campeche; 8, 12, 14, 15, 16 fracción II, y 22 fracciones II, VII y XXXVIII de la Ley\nOrgánica de la Administración Pública del Estado de Campeche, y los artículos 1, 3 inciso A fracción\nI, 9 y 10 fracciones IV, VII y XXVI del Reglamento Interior de la Secretaría de Finanzas de la\nAdministración Pública del Estado de Campeche, y\nCONSIDERANDO:\nQue el penúltimo párrafo del artículo 6 de la Ley de Coordinación Fiscal establece que las publicaciones en él referidas deberán realizarse conforme a los lineamientos que al efecto emita la\nSecretaría de Hacienda y Crédito Público.\nQue el 14 de febrero de 2014, la Secretaría de Hacienda y Crédito Público, a través del Diario Oficial de la Federación el Acuerdo 02/2014 por el que se expiden los Lineamientos para la publicación de la información a que se refiere el artículo 6 de la Ley de Coordinación Fiscal.\nQue el Gobierno Federal, por conducto de la Secretaría de Hacienda y Crédito Público, celebró el\nConvenio de Colaboración Administrativa en Materia Fiscal Federal con el Estado de Campeche, mismo que fue publicado en el Diario Oficial de la Federación el 27 de julio de 2015 y en el Periódico\nOficial del Estado el 31 de julio de 2015.\nQue el 13 de febrero de 2020 se publicó en el Periódico Oficial del Estado el Acuerdo del Ejecutivo del Estado de Campeche en el que se da a conocer el Calendario de Entrega, Porcentaje, Fórmulas y Variables Utilizadas, así como los montos estimados, de las participaciones que el Estado de\nCampeche reciba y de las que tengan obligación de participar a sus municipios en el ejercicio fiscal\n2020.\nQue conforme a los anteriores considerandos, y en cumplimiento a la obligación prevista en el artículo 6 cuarto párrafo de la Ley de Coordinación Fiscal, tengo a bien emitir el siguiente:\nACUERDO DEL EJECUTIVO DEL ESTADO POR EL QUE SE DA A CONOCER EL IMPORTE DE\nLAS PARTICIPACIONES FEDERALES ENTREGADAS A LOS MUNICIPIOS, EN EL PERÍODO\nCOMPRENDIDO DEL 1° DE ENERO AL 31 DE MARZO 2020, A QUE SE REFIERE EL ARTICULO\n6° DE LA LEY DE COORDINACION FISCAL\nPRIMERO.- El importe trimestral de las participaciones federales derivadas del Fondo General de\nParticipaciones y del Fondo de Fomento Municipal, así como de las correspondientes al Impuesto\nSobre Automóviles Nuevos, Impuesto Sobre Tenencia o Uso de Vehículos parte Federal, Impuesto\nEspecial Sobre Producción y Servicios, Fondo de Fiscalización y Recaudación, Cuotas de Gasolinas y Diésel, Artículo 4°-A fracción II de la Ley de Coordinación Fiscal, Fondo de Compensación del\nImpuesto Sobre Automóviles Nuevos, Fondo de Extracción de Hidrocarburos, Fondo de Impuesto\nSobre la Renta, entregados a los municipios en el período comprendido del 1° de Enero al 31 de\nMarzo del ejercicio fiscal 2020 es el siguiente:\nFISCAL 2020\n(Formato III del Acuerdo 02/2014)\nCALAKMUL 14,163,462 3,217,545 413,963 110,864 0 121,125 585,021 213,524 0 28,876 5,210,828 3,084,909 27,150,118\nCALKINI 20,291,220 4,603,267 981,273 158,120 0 175,311 836,452 434,264 0 41,099 7,301,778 1,083,359 35,906,143\nCAMPECHE 90,902,339 20,557,793 4,86 4 6,64 701,166 0 803,467 3,430,311 2,583,684 0 181,372 24,790,682 16,1 4 4 5,48 164,9 2 6 2,94\nCANDELARIA 18,598,838 4,222,790 867,695 145,319 0 159,716 753,458 328,136 0 37,819 6,516,252 3,779,957 35,409,979\nCARMEN 81,666,422 18,483,679 3,44 9 4,23 631,560 0 717,722 3,173,998 2,197,507 0 163,568 24,828,210 43,8 3 7 6,01 179,1 8 8 2,91\nCHAMPOTÓN 31,360,208 7,108,934 2,81 6 7,55 243,767 0 272,476 1,188,213 789,803 0 63,286 11,831,249 1,655,091 57,330,583\nESCÁRCEGA 23,114,827 5,243,693 968,915 180,108 0 199,745 896,901 461,129 0 46,812 7,132,372 523,633 38,768,135\nHOPELCHEN 17,528,393 3,978,970 712,321 136,868 0 150,744 656,555 308,525 0 35,609 6,507,343 910,713 30,926,042\nPALIZADA 15,598,490 3,551,068 187,446 122,939 0 131,280 538,920 71,369 0 32,124 6,354,174 4,131,285 30,719,095\nTENABO 11,216,674 2,552,329 187,739 88,269 0 94,739 407,769 82,500 0 23,048 3,747,779 496,570 18,897,416\nTOTAL 338,364,122 76,681,464 15, 9 9 0 8 8,9 2,627,788 0 2,945,838 13,022,779 7,708,576 0 681,934 109,103,474 77,0 2 0 4,73 644,1 6 2 9,69\n* Ingresos causados en ejercicios fiscales anteriores al ejercicio 2010.\nSEGUNDO.- El importe con desglose mensual de las participaciones federales derivadas del Fondo\nGeneral de Participaciones y del Fondo de Fomento Municipal, así como de las correspondientes al\n{\"tabla_1\":{\"columnas\":[\"Municipio\\nCALAKMUL\",\"Participaciones\\n4,390,252\",\"70%\\n1,030,810\",\"30%\\n88,471\",\"Automóvile\\ns Nuevos\\n44,782\",\"Uso de\\nVehículos*\\n0\",\"Producción y\\nServicios\\n39,316\",\"Recaudació\\nn /1\\n230,497\",\"Coordinación\\nFiscal\\n(Gasolinas)\\n63,628\",\"Coordinación\\nFiscal\\n(FOCO)\\n0\",\"Sobre\\nAutomóviles\\nNuevos\\n9,993\",\"Hidrocarburos\\n1,816,302\",\"566,677\",\"8,280,728\"],\"filas\":[{\"columna_1\":\"CALKINI\",\"columna_2\":\"6,118,383\",\"columna_3\":\"1,436,568\",\"columna_4\":\"209,715\",\"columna_5\":\"62,409\",\"columna_6\":\"0\",\"columna_7\":\"54,792\",\"columna_8\":\"350,379\",\"columna_9\":\"129,406\",\"columna_10\":\"0\",\"columna_11\":\"13,926\",\"columna_12\":\"2,571,834\",\"columna_13\":\"79,075\",\"columna_14\":\"11,026,48\\n7\"},{\"columna_1\":\"CAMPECHE\",\"columna_2\":\"25,670,214\",\"columna_3\":\"6,027,246\",\"columna_4\":\"1,040,087\",\"columna_5\":\"261,843\",\"columna_6\":\"0\",\"columna_7\":\"229,883\",\"columna_8\":\"1,674,403\",\"columna_9\":\"769,910\",\"columna_10\":\"0\",\"columna_11\":\"58,429\",\"columna_12\":\"9,084,088\",\"columna_13\":\"10,311,47\\n0\",\"columna_14\":\"55,127,57\\n3\"},{\"columna_1\":\"CANDELARIA\",\"columna_2\":\"5,701,578\",\"columna_3\":\"1,338,704\",\"columna_4\":\"185,441\",\"columna_5\":\"58,158\",\"columna_6\":\"0\",\"columna_7\":\"51,059\",\"columna_8\":\"305,438\",\"columna_9\":\"97,781\",\"columna_10\":\"0\",\"columna_11\":\"12,978\",\"columna_12\":\"2,283,439\",\"columna_13\":\"2,304,044\",\"columna_14\":\"12,338,61\\n9\"},{\"columna_1\":\"CARMEN\",\"columna_2\":\"23,457,249\",\"columna_3\":\"5,507,652\",\"columna_4\":\"736,094\",\"columna_5\":\"239,270\",\"columna_6\":\"0\",\"columna_7\":\"210,066\",\"columna_8\":\"1,487,221\",\"columna_9\":\"654,833\",\"columna_10\":\"0\",\"columna_11\":\"53,392\",\"columna_12\":\"8,972,394\",\"columna_13\":\"35,548,09\\n4\",\"columna_14\":\"76,866,26\\n4\"},{\"columna_1\":\"CHAMPOTÓN\",\"columna_2\":\"9,308,752\",\"columna_3\":\"2,185,651\",\"columna_4\":\"602,161\",\"columna_5\":\"94,952\",\"columna_6\":\"0\",\"columna_7\":\"83,362\",\"columna_8\":\"524,479\",\"columna_9\":\"235,353\",\"columna_10\":\"0\",\"columna_11\":\"21,188\",\"columna_12\":\"4,182,441\",\"columna_13\":\"26,770\",\"columna_14\":\"17,265,10\\n9\"},{\"columna_1\":\"ESCÁRCEGA\",\"columna_2\":\"6,966,059\",\"columna_3\":\"1,635,598\",\"columna_4\":\"207,074\",\"columna_5\":\"71,056\",\"columna_6\":\"0\",\"columna_7\":\"62,383\",\"columna_8\":\"380,937\",\"columna_9\":\"137,411\",\"columna_10\":\"0\",\"columna_11\":\"15,856\",\"columna_12\":\"2,526,929\",\"columna_13\":\"270,005\",\"columna_14\":\"12,273,30\\n8\"},{\"columna_1\":\"HECELCHAKAN\",\"columna_2\":\"4,273,112\",\"columna_3\":\"1,003,307\",\"columna_4\":\"115,664\",\"columna_5\":\"43,587\",\"columna_6\":\"0\",\"columna_7\":\"38,267\",\"columna_8\":\"225,111\",\"columna_9\":\"70,961\",\"columna_10\":\"0\",\"columna_11\":\"9,726\",\"columna_12\":\"1,710,276\",\"columna_13\":\"0\",\"columna_14\":\"7,490,011\"},{\"columna_1\":\"HOPELCHEN\",\"columna_2\":\"5,352,319\",\"columna_3\":\"1,256,699\",\"columna_4\":\"152,235\",\"columna_5\":\"54,595\",\"columna_6\":\"0\",\"columna_7\":\"47,931\",\"columna_8\":\"272,566\",\"columna_9\":\"91,937\",\"columna_10\":\"0\",\"columna_11\":\"12,183\",\"columna_12\":\"2,279,709\",\"columna_13\":\"0\",\"columna_14\":\"9,520,175\"}]}}\nPALIZADA 5,038,581 1,183,035 40,060 51,395 0 45,122 194,112 21,267 0 11,468 2,179,593 2,943,896 11,7 0 0 8,53\nTENABO 3,590,773 843,097 40,123 36,627 0 32,156 150,249 24,584 0 8,173 1,292,636 194,180 6,212,599\n{\"tabla_2\":{\"columnas\":[\"Municipio\\nCALAKMUL\",\"Participaciones\\n/2\\n5,367,812\",\"70%\\n1,153,609\",\"30%\\n236,053\",\"Automóvil\\nes Nuevos\\n37,502\",\"Tenencia o\\nUso de\\nVehículos*\\n0\",\"Producció\\nn y\\nServicios\\n/2\\n46,532\",\"y\\nRecaudación\\n177,262\",\"Coordinación\\nFiscal\\n(Gasolinas)\\n77,499\",\"Coordinación\\nFiscal\\n(FOCO)\\n0\",\"Impuesto\\nSobre\\nAutomóviles\\nNuevos\\n8,887\",\"Extracción de\\nHidrocarburos\\n1,758,747\",\"ISR\\n2,098,978\",\"Total\\n10,962,880\",\"(sin encabezado)\",\"(sin encabezado)\"],\"filas\":[{\"columna_1\":\"CALKINI\",\"columna_2\":\"8,034,725\",\"columna_3\":\"1,727,230\",\"columna_4\":\"559,549\",\"columna_5\":\"55,889\",\"columna_6\":\"0\",\"columna_7\":\"71,367\",\"columna_8\":\"243,036\",\"columna_9\":\"157,617\",\"columna_10\":\"0\",\"columna_11\":\"13,244\",\"columna_12\":\"2,455,783\",\"columna_13\":\"1,004,284\",\"columna_14\":\"14,322,724\",\"columna_15\":\"(sin dato)\",\"columna_16\":\"(sin dato)\"},{\"columna_1\":\"CAMPECHE\",\"columna_2\":\"39,493,551\",\"columna_3\":\"8,494,506\",\"columna_4\":\"2,775,094\",\"columna_5\":\"272,339\",\"columna_6\":\"0\",\"columna_7\":\"367,478\",\"columna_8\":\"877,954\",\"columna_9\":\"937,750\",\"columna_10\":\"0\",\"columna_11\":\"64,537\",\"columna_12\":\"8,223,024\",\"columna_13\":\"1,466,477\",\"columna_14\":\"62,972,711\",\"columna_15\":\"(sin dato)\",\"columna_16\":\"(sin dato)\"},{\"columna_1\":\"CANDELARIA\",\"columna_2\":\"7,176,523\",\"columna_3\":\"1,542,497\",\"columna_4\":\"494,783\",\"columna_5\":\"50,047\",\"columna_6\":\"0\",\"columna_7\":\"62,848\",\"columna_8\":\"224,010\",\"columna_9\":\"119,097\",\"columna_10\":\"0\",\"columna_11\":\"11,860\",\"columna_12\":\"2,195,405\",\"columna_13\":\"733,077\",\"columna_14\":\"12,610,147\",\"columna_15\":\"(sin dato)\",\"columna_16\":\"(sin dato)\"},{\"columna_1\":\"CARMEN\",\"columna_2\":\"34,685,962\",\"columna_3\":\"7,459,519\",\"columna_4\":\"1,964,000\",\"columna_5\":\"239,679\",\"columna_6\":\"0\",\"columna_7\":\"319,290\",\"columna_8\":\"843,389\",\"columna_9\":\"797,587\",\"columna_10\":\"0\",\"columna_11\":\"56,797\",\"columna_12\":\"8,276,329\",\"columna_13\":\"7,907,439\",\"columna_14\":\"62,549,990\",\"columna_15\":\"(sin dato)\",\"columna_16\":\"(sin dato)\"},{\"columna_1\":\"CHAMPOTÓN\",\"columna_2\":\"12,713,908\",\"columna_3\":\"2,733,502\",\"columna_4\":\"1,606,648\",\"columna_5\":\"88,236\",\"columna_6\":\"0\",\"columna_7\":\"114,342\",\"columna_8\":\"331,867\",\"columna_9\":\"286,660\",\"columna_10\":\"0\",\"columna_11\":\"20,909\",\"columna_12\":\"3,974,202\",\"columna_13\":\"1,574,098\",\"columna_14\":\"23,444,373\",\"columna_15\":\"(sin dato)\",\"columna_16\":\"(sin dato)\"},{\"columna_1\":\"ESCÁRCEGA\",\"columna_2\":\"9,160,277\",\"columna_3\":\"1,969,201\",\"columna_4\":\"552,502\",\"columna_5\":\"63,713\",\"columna_6\":\"0\",\"columna_7\":\"81,400\",\"columna_8\":\"257,982\",\"columna_9\":\"167,367\",\"columna_10\":\"0\",\"columna_11\":\"15,098\",\"columna_12\":\"2,393,998\",\"columna_13\":\"0\",\"columna_14\":\"14,661,539\",\"columna_15\":\"(sin dato)\",\"columna_16\":\"(sin dato)\"},{\"columna_1\":\"HECELCHAKAN\",\"columna_2\":\"5,362,626\",\"columna_3\":\"1,152,611\",\"columna_4\":\"308,607\",\"columna_5\":\"37,404\",\"columna_6\":\"0\",\"columna_7\":\"46,915\",\"columna_8\":\"165,035\",\"columna_9\":\"86,431\",\"columna_10\":\"0\",\"columna_11\":\"8,864\",\"columna_12\":\"1,645,327\",\"columna_13\":\"1,269,055\",\"columna_14\":\"10,082,875\",\"columna_15\":\"(sin dato)\",\"columna_16\":\"(sin dato)\"},{\"columna_1\":\"HOPELCHEN\",\"columna_2\":\"6,805,942\",\"columna_3\":\"1,462,902\",\"columna_4\":\"406,185\",\"columna_5\":\"47,433\",\"columna_6\":\"0\",\"columna_7\":\"59,810\",\"columna_8\":\"191,995\",\"columna_9\":\"111,980\",\"columna_10\":\"0\",\"columna_11\":\"11,240\",\"columna_12\":\"2,192,602\",\"columna_13\":\"735,697\",\"columna_14\":\"12,025,786\",\"columna_15\":\"(sin dato)\",\"columna_16\":\"(sin dato)\"},{\"columna_1\":\"PALIZADA\",\"columna_2\":\"5,502,303\",\"columna_3\":\"1,181,956\",\"columna_4\":\"106,887\",\"columna_5\":\"38,732\",\"columna_6\":\"0\",\"columna_7\":\"45,659\",\"columna_8\":\"172,404\",\"columna_9\":\"25,904\",\"columna_10\":\"0\",\"columna_11\":\"9,178\",\"columna_12\":\"2,156,123\",\"columna_13\":\"609,619\",\"columna_14\":\"9,848,764\",\"columna_15\":\"(sin dato)\",\"columna_16\":\"(sin dato)\"},{\"columna_1\":\"TENABO\",\"columna_2\":\"4,021,820\",\"columna_3\":\"864,027\",\"columna_4\":\"107,054\",\"columna_5\":\"28,261\",\"columna_6\":\"0\",\"columna_7\":\"33,722\",\"columna_8\":\"128,760\",\"columna_9\":\"29,943\",\"columna_10\":\"0\",\"columna_11\":\"6,697\",\"columna_12\":\"1,269,404\",\"columna_13\":\"297,849\",\"columna_14\":\"6,787,537\",\"columna_15\":\"(sin dato)\",\"columna_16\":\"(sin dato)\"},{\"columna_1\":\"TOTAL\",\"columna_2\":\"138,325,449\",\"columna_3\":\"29,741,56\\n2\",\"columna_4\":\"9,117,361\",\"columna_5\":\"959,236\",\"columna_6\":\"0\",\"columna_7\":\"1,249,363\",\"columna_8\":\"3,613,693\",\"columna_9\":\"2,797,833\",\"columna_10\":\"0\",\"columna_11\":\"227,311\",\"columna_12\":\"36,540,944\",\"columna_13\":\"17,696,57\\n3\",\"columna_14\":\"(sin dato)\",\"columna_15\":\"240,269,32\",\"columna_16\":\"(sin dato)\"},{\"columna_1\":\"(sin dato)\",\"columna_2\":\"(sin dato)\",\"columna_3\":\"(sin dato)\",\"columna_4\":\"(sin dato)\",\"columna_5\":\"(sin dato)\",\"columna_6\":\"(sin dato)\",\"columna_7\":\"(sin dato)\",\"columna_8\":\"(sin dato)\",\"columna_9\":\"(sin dato)\",\"columna_10\":\"(sin dato)\",\"columna_11\":\"(sin dato)\",\"columna_12\":\"(sin dato)\",\"columna_13\":\"(sin dato)\",\"columna_14\":\"(sin dato)\",\"columna_15\":\"5\",\"columna_16\":\"(sin dato)\"}]}}\nTRANSITORIO\nÚnico. - El presente Acuerdo entrará en vigor al día siguiente de su publicación en el Periódico Oficial del Estado.\nSan Francisco de Campeche, Municipio y Estado de Campeche, al primer día del mes de abril de 2020\nLIC. CARLOS MIGUEL AYSA GONZÁLEZ\nGOBERNADOR DEL ESTADO DE CAMPECHE\nC. P. GUADALUPE ESTHER CÁRDENAS GUERRERO\nSECRETARIA DE FINANZAS",
  "ordenamiento": "ACUERDO",
  "jurisdiccion": "CAMPECHE",
  "fuente_oficial": "DIARIO OFICIAL DE LA FEDERACION",
  "Fecha de Publicación": "31 DE MARZO DE 2020",
  "es_escaneado": false,
  "tiene_tablas": true,
  "materia": [
    "general"
  ]
}